smtp2go/__init__.py
smtp2go/core.py
smtp2go/exceptions.py
smtp2go/settings.py
smtp2go-2.3.1.dist-info/LICENSE.txt
smtp2go-2.3.1.dist-info/METADATA
smtp2go-2.3.1.dist-info/WHEEL
smtp2go-2.3.1.dist-info/top_level.txt
smtp2go-2.3.1.dist-info/RECORD
