Metadata-Version: 2.1
Name: smtp2go
Version: 2.3.1
Summary: Library for interfacing with the smtp2go API.
Home-page: https://github.com/smtp2go-oss/smtp2go-python
Author: smtp2go
Author-email: devs@smtp2go.com
License: MIT
Platform: UNKNOWN
Classifier: Development Status :: 5 - Production/Stable
Classifier: Intended Audience :: Developers
Classifier: License :: OSI Approved :: MIT License
Classifier: Programming Language :: Python :: 2.7
Classifier: Programming Language :: Python :: 3
Classifier: Topic :: Communications :: Email
Classifier: Topic :: Software Development :: Libraries :: Python Modules
Requires-Dist: requests
